neurommsig_epilepsy/__init__.py
neurommsig_epilepsy/__main__.py
neurommsig_epilepsy-0.0.1.dist-info/LICENSE
neurommsig_epilepsy-0.0.1.dist-info/METADATA
neurommsig_epilepsy-0.0.1.dist-info/WHEEL
neurommsig_epilepsy-0.0.1.dist-info/entry_points.txt
neurommsig_epilepsy-0.0.1.dist-info/top_level.txt
neurommsig_epilepsy-0.0.1.dist-info/RECORD
