Metadata-Version: 2.1
Name: neurommsig-epilepsy
Version: 0.0.1
Summary: Mechanistic pathway knowledge on Epilepsy encoded in Biological Expression Language
Home-page: https://github.com/neurommsig-epilepsy/neurommsig-epilepsy
Author: Daniel Domingo-Fernández
Author-email: daniel.domingo.fernandez@scai.fraunhofer.de
Maintainer: Charles Tapley Hoyt
Maintainer-email: cthoyt@gmail.com
License: UNKNOWN
Download-URL: https://github.com/neurommsig-epilepsy/neurommsig-epilepsy/releases
Project-URL: Bug Tracker, https://github.com/neurommsig-epilepsy/neurommsig-epilepsy/issues
Project-URL: Source Code, https://github.com/neurommsig-epilepsy/neurommsig-epilepsy
Platform: UNKNOWN
Requires-Python: >=3.6
Requires-Dist: pybel
